README.rst
setup.cfg
setup.py
charlesbot/__init__.py
charlesbot/__main__.py
charlesbot/base_object.py
charlesbot/base_plugin.py
charlesbot/robot.py
charlesbot.egg-info/PKG-INFO
charlesbot.egg-info/SOURCES.txt
charlesbot.egg-info/dependency_links.txt
charlesbot.egg-info/entry_points.txt
charlesbot.egg-info/pbr.json
charlesbot.egg-info/requires.txt
charlesbot.egg-info/top_level.txt
charlesbot/config/__init__.py
charlesbot/config/configuration.py
charlesbot/plugins/__init__.py
charlesbot/plugins/help_plugin.py
charlesbot/plugins/ping_plugin.py
charlesbot/slack/__init__.py
charlesbot/slack/slack_attachment.py
charlesbot/slack/slack_base_object.py
charlesbot/slack/slack_channel_joined.py
charlesbot/slack/slack_channel_left.py
charlesbot/slack/slack_connection.py
charlesbot/slack/slack_group_joined.py
charlesbot/slack/slack_group_left.py
charlesbot/slack/slack_message.py
charlesbot/slack/slack_pong.py
charlesbot/slack/slack_room_joined.py
charlesbot/slack/slack_user.py
charlesbot/util/__init__.py
charlesbot/util/borg.py
charlesbot/util/http.py
charlesbot/util/parse.py
charlesbot/util/slack.py
tests/config/__init__.py
tests/config/test_configuration.py
tests/plugins/__init__.py
tests/plugins/help_plugin/__init__.py
tests/plugins/help_plugin/test_help_plugin.py
tests/plugins/ping_plugin/__init__.py
tests/plugins/ping_plugin/test_ping_plugin.py
tests/slack/__init__.py
tests/slack/test_slack_attachment.py
tests/slack/test_slack_base_object.py
tests/slack/test_slack_base_object_children.py
tests/slack/test_slack_connection_api_call.py
tests/slack/test_slack_connection_stream_messages.py
tests/slack/test_slack_room_joined.py
tests/slack/test_slack_user.py
tests/util/__init__.py
tests/util/http/__init__.py
tests/util/http/test_get_auth_request.py
tests/util/http/test_get_request.py
tests/util/parse/__init__.py
tests/util/parse/test_does_msg_contain_prefix.py
tests/util/parse/test_message_parser.py
tests/util/slack/__init__.py
tests/util/slack/test_get_robot_channel_membership.py
tests/util/slack/test_get_robot_group_membership.py
tests/util/slack/test_get_robot_info.py