Metadata-Version: 1.1
Name: charlesbot
Version: 0.10.1
Summary: CharlesBOT is a Python bot written to take advantage of Slack's Real Time Messaging API
Home-page: https://github.com/marvinpinto/charlesbot
Author: Marvin Pinto
Author-email: marvin@pinto.im
License: MIT
Keywords: slack robot chatops automation
Platform: UNKNOWN
Classifier: Development Status :: 3 - Alpha
Classifier: Intended Audience :: Developers
Classifier: License :: OSI Approved :: MIT License
Classifier: Programming Language :: Python :: 3.4
